t212/__init__.py
t212/async_client.py
t212/client.py
t212/config.py
t212/exceptions.py
t212/models.py
trading_212_client-0.1.4.dist-info/METADATA
trading_212_client-0.1.4.dist-info/WHEEL
trading_212_client-0.1.4.dist-info/RECORD
