Metadata-Version: 2.3
Name: trading-212-client
Version: 0.1.4
Summary: 
Author: Lancasterg
Author-email: lancaster0180@gmail.com
Requires-Python: >=3.11,<4.0
Classifier: Programming Language :: Python :: 3
Classifier: Programming Language :: Python :: 3.11
Classifier: Programming Language :: Python :: 3.12
Classifier: Programming Language :: Python :: 3.13
Requires-Dist: aiohttp (>=3.12.15,<4.0.0)
Requires-Dist: pydantic (>=2.11.7,<3.0.0)
Requires-Dist: requests (>=2.32.5,<3.0.0)
